{
  "metadata": {
    "manufacturer": "Wolfspeed",
    "type": "MOSFET with Diode",
    "material": "SiC",
    "package_type": "discrete",
    "part_number": "C3M0120100J",
    "author": "Fulong Li",
    "date": "2026-01-11 23:42:49",
    "source_file": "C3M0120100J.xml",
    "source_path": "SiC\\Wolfspeed\\MOSFET with Diode\\MOSFETs\\C3M0120100J.xml"
  },
  "library": {
    "xmlns": "",
    "version": "1.4"
  },
  "package": {
    "class": "MOSFET with Diode",
    "vendor": "Wolfspeed",
    "partnumber": "C3M0120100J",
    "variables": [
      {
        "name": "Rgon",
        "description": "External gate resistance (turn-on)",
        "default_value": 2.5,
        "min_value": 2.5,
        "max_value": 20.0
      },
      {
        "name": "Rgoff",
        "description": "External gate resistance (turn-off)",
        "default_value": 2.5,
        "min_value": 2.5,
        "max_value": 20.0
      }
    ],
    "semiconductor_data": {
      "type": "MOSFET with Diode",
      "turn_on_loss": {
        "computation_method": "Table and formula",
        "formula": "E/(2.6704e-6*2.5+40.619e-6)*(2.6704e-6*Rgon+40.619e-6)",
        "current_axis": [
          -10.0,
          0.0,
          2.82,
          5.92,
          8.855,
          11.8,
          14.82,
          17.8,
          20.57,
          23.61
        ],
        "voltage_axis": [
          -100.0,
          0.0,
          400.0,
          600.0
        ],
        "temperature_axis": [
          -55.0,
          25.0,
          150.0,
          900.0,
          1000.0
        ],
        "energy": {
          "scale": 1e-06,
          "data": [
            [
              [
                0.0,
                0.0,
                0.0,
                0.0,
                0.0,
                0.0,
                0.0,
                0.0,
                0.0,
                0.0
              ],
              [
                0.0,
                0.0,
                0.0,
                0.0,
                0.0,
                0.0,
                0.0,
                0.0,
                0.0,
                0.0
              ],
              [
                0.0,
                0.0,
                33.67,
                41.68,
                49.92,
                59.48,
                71.44,
                83.0,
                96.04,
                111.7
              ],
              [
                0.0,
                0.0,
                70.34,
                85.81,
                103.5,
                122.6,
                140.9,
                161.3,
                189.7,
                217.6
              ]
            ],
            [
              [
                0.0,
                0.0,
                0.0,
                0.0,
                0.0,
                0.0,
                0.0,
                0.0,
                0.0,
                0.0
              ],
              [
                0.0,
                0.0,
                0.0,
                0.0,
                0.0,
                0.0,
                0.0,
                0.0,
                0.0,
                0.0
              ],
              [
                0.0,
                0.0,
                21.93,
                27.15,
                32.52,
                38.75,
                46.54,
                54.07,
                62.57,
                72.75
              ],
              [
                0.0,
                0.0,
                45.83,
                55.9,
                67.44,
                79.85,
                91.78,
                105.1,
                123.6,
                141.8
              ]
            ],
            [
              [
                0.0,
                0.0,
                0.0,
                0.0,
                0.0,
                0.0,
                0.0,
                0.0,
                0.0,
                0.0
              ],
              [
                0.0,
                0.0,
                0.0,
                0.0,
                0.0,
                0.0,
                0.0,
                0.0,
                0.0,
                0.0
              ],
              [
                0.0,
                0.0,
                22.9,
                28.35,
                33.95,
                40.45,
                48.59,
                56.45,
                65.32,
                75.95
              ],
              [
                0.0,
                0.0,
                47.84,
                58.36,
                70.41,
                83.37,
                95.82,
                109.7,
                129.0,
                148.0
              ]
            ],
            [
              [
                0.0,
                0.0,
                0.0,
                0.0,
                0.0,
                0.0,
                0.0,
                0.0,
                0.0,
                0.0
              ],
              [
                0.0,
                0.0,
                0.0,
                0.0,
                0.0,
                0.0,
                0.0,
                0.0,
                0.0,
                0.0
              ],
              [
                0.0,
                0.0,
                33.67,
                41.68,
                49.92,
                59.48,
                71.44,
                83.0,
                96.04,
                111.7
              ],
              [
                0.0,
                0.0,
                70.34,
                85.81,
                103.5,
                122.6,
                140.9,
                161.3,
                189.7,
                217.6
              ]
            ],
            [
              [
                0.0,
                0.0,
                0.0,
                0.0,
                0.0,
                0.0,
                0.0,
                0.0,
                0.0,
                0.0
              ],
              [
                0.0,
                0.0,
                0.0,
                0.0,
                0.0,
                0.0,
                0.0,
                0.0,
                0.0,
                0.0
              ],
              [
                0.0,
                0.0,
                33.67,
                41.68,
                49.92,
                59.48,
                71.44,
                83.0,
                96.04,
                111.7
              ],
              [
                0.0,
                0.0,
                70.34,
                85.81,
                103.5,
                122.6,
                140.9,
                161.3,
                189.7,
                217.6
              ]
            ]
          ]
        }
      },
      "turn_off_loss": {
        "computation_method": "Table and formula",
        "formula": "E/(0.7882e-6*2.5+14.634e-6)*(0.7882e-6*Rgoff+14.634e-6)",
        "current_axis": [
          -10.0,
          0.0,
          2.82,
          5.92,
          8.855,
          11.8,
          14.82,
          17.8,
          20.57,
          23.61
        ],
        "voltage_axis": [
          -100.0,
          0.0,
          400.0,
          600.0
        ],
        "temperature_axis": [
          -55.0,
          25.0,
          125.0,
          900.0,
          1000.0
        ],
        "energy": {
          "scale": 1e-06,
          "data": [
            [
              [
                0.0,
                0.0,
                0.0,
                0.0,
                0.0,
                0.0,
                0.0,
                0.0,
                0.0,
                0.0
              ],
              [
                0.0,
                0.0,
                0.0,
                0.0,
                0.0,
                0.0,
                0.0,
                0.0,
                0.0,
                0.0
              ],
              [
                0.0,
                0.0,
                5.93,
                6.32,
                9.25,
                12.79,
                16.04,
                20.42,
                26.28,
                32.74
              ],
              [
                0.0,
                0.0,
                12.12,
                12.15,
                14.0,
                19.8,
                28.52,
                35.66,
                40.36,
                49.94
              ]
            ],
            [
              [
                0.0,
                0.0,
                0.0,
                0.0,
                0.0,
                0.0,
                0.0,
                0.0,
                0.0,
                0.0
              ],
              [
                0.0,
                0.0,
                0.0,
                0.0,
                0.0,
                0.0,
                0.0,
                0.0,
                0.0,
                0.0
              ],
              [
                0.0,
                0.0,
                5.93,
                6.32,
                9.25,
                12.79,
                16.04,
                20.42,
                26.28,
                32.74
              ],
              [
                0.0,
                0.0,
                12.12,
                12.15,
                14.0,
                19.8,
                28.52,
                35.66,
                40.36,
                49.94
              ]
            ],
            [
              [
                0.0,
                0.0,
                0.0,
                0.0,
                0.0,
                0.0,
                0.0,
                0.0,
                0.0,
                0.0
              ],
              [
                0.0,
                0.0,
                0.0,
                0.0,
                0.0,
                0.0,
                0.0,
                0.0,
                0.0,
                0.0
              ],
              [
                0.0,
                0.0,
                5.93,
                6.32,
                9.25,
                12.79,
                16.04,
                20.42,
                26.28,
                32.74
              ],
              [
                0.0,
                0.0,
                12.12,
                12.15,
                14.0,
                19.8,
                28.52,
                35.66,
                40.36,
                49.94
              ]
            ],
            [
              [
                0.0,
                0.0,
                0.0,
                0.0,
                0.0,
                0.0,
                0.0,
                0.0,
                0.0,
                0.0
              ],
              [
                0.0,
                0.0,
                0.0,
                0.0,
                0.0,
                0.0,
                0.0,
                0.0,
                0.0,
                0.0
              ],
              [
                0.0,
                0.0,
                5.93,
                6.32,
                9.25,
                12.79,
                16.04,
                20.42,
                26.28,
                32.74
              ],
              [
                0.0,
                0.0,
                12.12,
                12.15,
                14.0,
                19.8,
                28.52,
                35.66,
                40.36,
                49.94
              ]
            ],
            [
              [
                0.0,
                0.0,
                0.0,
                0.0,
                0.0,
                0.0,
                0.0,
                0.0,
                0.0,
                0.0
              ],
              [
                0.0,
                0.0,
                0.0,
                0.0,
                0.0,
                0.0,
                0.0,
                0.0,
                0.0,
                0.0
              ],
              [
                0.0,
                0.0,
                5.93,
                6.32,
                9.25,
                12.79,
                16.04,
                20.42,
                26.28,
                32.74
              ],
              [
                0.0,
                0.0,
                12.12,
                12.15,
                14.0,
                19.8,
                28.52,
                35.66,
                40.36,
                49.94
              ]
            ]
          ]
        }
      },
      "conduction_loss": [
        {
          "computation_method": "Table only",
          "current_axis": [
            -40.0,
            -30.0,
            -20.0,
            -10.0,
            -5.0,
            0.0,
            5.0,
            15.0,
            25.0,
            35.0,
            45.0
          ],
          "temperature_axis": [
            -55.0,
            25.0,
            150.0,
            900.0,
            1000.0
          ],
          "voltage_drop": {
            "scale": 1.0,
            "data": [
              [
                -3.583,
                -2.802,
                -1.975,
                -1.047,
                -0.55,
                0.0,
                0.613,
                1.952,
                3.46,
                5.108,
                7.009
              ],
              [
                -3.908,
                -2.985,
                -2.032,
                -1.05,
                -0.53,
                0.0,
                0.556,
                1.799,
                3.185,
                4.814,
                6.83
              ],
              [
                -5.9,
                -4.57,
                -3.079,
                -1.571,
                -0.796,
                0.0,
                0.805,
                2.523,
                4.53,
                7.044,
                10.76
              ],
              [
                -5.933,
                -4.612,
                -3.103,
                -1.599,
                -0.811,
                0.0,
                0.815,
                2.555,
                4.552,
                7.099,
                10.78
              ],
              [
                -5.933,
                -4.612,
                -3.103,
                -1.599,
                -0.811,
                0.0,
                0.815,
                2.555,
                4.552,
                7.099,
                10.78
              ]
            ]
          },
          "gate": "on"
        },
        {
          "computation_method": "Table only",
          "current_axis": [
            -45.0,
            -40.0,
            -35.0,
            -30.0,
            -25.0,
            -20.0,
            -15.0,
            -10.0,
            -5.0,
            -0.594,
            -0.104,
            0.0,
            1.0
          ],
          "temperature_axis": [
            -55.0,
            25.0,
            150.0,
            900.0,
            1000.0
          ],
          "voltage_drop": {
            "scale": 1.0,
            "data": [
              [
                -8.664,
                -8.4145,
                -8.09,
                -7.755,
                -7.39,
                -6.97,
                -6.47,
                -5.898,
                -5.12,
                -3.744,
                -3.219,
                0.0,
                0.0
              ],
              [
                -7.662,
                -7.512,
                -7.188,
                -6.82,
                -6.45,
                -6.009,
                -5.52,
                -4.98,
                -4.35,
                -3.33,
                -2.83,
                0.0,
                0.0
              ],
              [
                -6.789,
                -6.739,
                -6.44,
                -6.12,
                -5.781,
                -5.38,
                -4.953,
                -4.4855,
                -3.863,
                -2.802,
                -2.41,
                0.0,
                0.0
              ],
              [
                -6.699,
                -6.622,
                -6.332,
                -6.05,
                -5.663,
                -5.289,
                -4.882,
                -4.375,
                -3.766,
                -2.756,
                -2.324,
                0.0,
                0.0
              ],
              [
                -6.699,
                -6.622,
                -6.332,
                -6.05,
                -5.663,
                -5.289,
                -4.882,
                -4.375,
                -3.766,
                -2.756,
                -2.324,
                0.0,
                0.0
              ]
            ]
          },
          "gate": "off"
        }
      ]
    },
    "thermal_model": {
      "type": "Cauer",
      "rc_elements": [
        {
          "R": 0.0725,
          "C": 0.00025
        },
        {
          "R": 0.725,
          "C": 0.00153
        },
        {
          "R": 0.3081,
          "C": 0.00383
        },
        {
          "R": 0.3793,
          "C": 0.03529
        }
      ]
    },
    "comment": [
      "-------------------------------------------------------------------------------------------------",
      "DISCLAIMER",
      "This model is provided as is, where is, and with no warranty of any kind either",
      "expressed or implied, including but not limited to any implied warranties of",
      "merchantability and fitness for a particular purpose.",
      "-------------------------------------------------------------------------------------------------",
      "",
      "",
      "-------------------------------------------------------------------------------------------------",
      "Wolfspeed SiC MOSFET PLECS Library",
      "",
      "       C3M0120100J",
      "       MOSFET",
      "       Datasheet Rev.1, 2025-09-18",
      "       ",
      "       Electrical Parameters (nominal)",
      "       Ron = 0.144 Ω",
      "       Vf = 3.533 V",
      "       ",
      "-------------------------------------------------------------------------------------------------",
      "",
      "",
      "-------------------------------------------------------------------------------------------------",
      "To find other WOLFSPEED SiC models, please visit:",
      "https://www.wolfspeed.com/tools-and-support/power/ltspice-and-plecs-models/",
      "-------------------------------------------------------------------------------------------------"
    ]
  }
}