{
  "metadata": {
    "manufacturer": "Wolfspeed",
    "type": "MOSFET with Diode",
    "material": "SiC",
    "package_type": "discrete",
    "part_number": "E3M0060065D",
    "author": "Fulong Li",
    "date": "2026-01-11 19:32:52",
    "source_file": "E3M0060065D.xml",
    "source_path": "SiC\\Wolfspeed\\MOSFET with Diode\\MOSFETs\\E3M0060065D.xml"
  },
  "library": {
    "xmlns": "",
    "version": "1.4"
  },
  "package": {
    "class": "MOSFET with Diode",
    "vendor": "Wolfspeed",
    "partnumber": "E3M0060065D",
    "variables": [
      {
        "name": "Rgon",
        "description": "External gate resistance (turn-on)",
        "default_value": 2.5,
        "min_value": 2.5,
        "max_value": 20.0
      },
      {
        "name": "Rgoff",
        "description": "External gate resistance (turn-off)",
        "default_value": 2.5,
        "min_value": 2.5,
        "max_value": 20.0
      }
    ],
    "semiconductor_data": {
      "type": "MOSFET with Diode",
      "turn_on_loss": {
        "computation_method": "Table and formula",
        "formula": "E/(0.003*2.5+0.1411)*(0.003*Rgon+0.1411)",
        "current_axis": [
          -1.0,
          0.0,
          3.684140625,
          6.948046875,
          10.20679688,
          13.47585938,
          16.51289063,
          19.55765625,
          22.63765625,
          25.74859375
        ],
        "voltage_axis": [
          -10.0,
          0.0,
          400.0
        ],
        "temperature_axis": [
          25.0,
          75.0,
          125.0,
          175.0,
          900.0
        ],
        "energy": {
          "scale": 0.001,
          "data": [
            [
              [
                0.0,
                0.0,
                0.0,
                0.0,
                0.0,
                0.0,
                0.0,
                0.0,
                0.0,
                0.0
              ],
              [
                0.0,
                0.0,
                0.0,
                0.0,
                0.0,
                0.0,
                0.0,
                0.0,
                0.0,
                0.0
              ],
              [
                0.0,
                0.0,
                0.042836407,
                0.065613945,
                0.100194103,
                0.147978725,
                0.193573479,
                0.250141485,
                0.313270403,
                0.38745406
              ]
            ],
            [
              [
                0.0,
                0.0,
                0.0,
                0.0,
                0.0,
                0.0,
                0.0,
                0.0,
                0.0,
                0.0
              ],
              [
                0.0,
                0.0,
                0.0,
                0.0,
                0.0,
                0.0,
                0.0,
                0.0,
                0.0,
                0.0
              ],
              [
                0.0,
                0.0,
                0.041896554,
                0.065372038,
                0.10140801,
                0.149234745,
                0.196108327,
                0.255457146,
                0.321208293,
                0.396784984
              ]
            ],
            [
              [
                0.0,
                0.0,
                0.0,
                0.0,
                0.0,
                0.0,
                0.0,
                0.0,
                0.0,
                0.0
              ],
              [
                0.0,
                0.0,
                0.0,
                0.0,
                0.0,
                0.0,
                0.0,
                0.0,
                0.0,
                0.0
              ],
              [
                0.0,
                0.0,
                0.042440434,
                0.068542512,
                0.106575205,
                0.156417364,
                0.205829356,
                0.267114119,
                0.332042354,
                0.410201595
              ]
            ],
            [
              [
                0.0,
                0.0,
                0.0,
                0.0,
                0.0,
                0.0,
                0.0,
                0.0,
                0.0,
                0.0
              ],
              [
                0.0,
                0.0,
                0.0,
                0.0,
                0.0,
                0.0,
                0.0,
                0.0,
                0.0,
                0.0
              ],
              [
                0.0,
                0.0,
                0.043902274,
                0.073933763,
                0.116760152,
                0.168942246,
                0.221678404,
                0.284303973,
                0.354531241,
                0.434902905
              ]
            ],
            [
              [
                0.0,
                0.0,
                0.0,
                0.0,
                0.0,
                0.0,
                0.0,
                0.0,
                0.0,
                0.0
              ],
              [
                0.0,
                0.0,
                0.0,
                0.0,
                0.0,
                0.0,
                0.0,
                0.0,
                0.0,
                0.0
              ],
              [
                0.0,
                0.0,
                0.050487615,
                0.085023828,
                0.134274174,
                0.194283583,
                0.254930165,
                0.326949569,
                0.407710927,
                0.50013834
              ]
            ]
          ]
        }
      },
      "turn_off_loss": {
        "computation_method": "Table and formula",
        "formula": "E/(0.0025*2.5+0.0124)*(0.0025*Rgoff+0.0124)",
        "current_axis": [
          -1.0,
          0.0,
          3.684140625,
          6.948046875,
          10.20679688,
          13.47585938,
          16.51289063,
          19.55765625,
          22.63765625,
          25.74859375
        ],
        "voltage_axis": [
          -10.0,
          0.0,
          400.0
        ],
        "temperature_axis": [
          25.0,
          75.0,
          125.0,
          175.0,
          900.0
        ],
        "energy": {
          "scale": 0.001,
          "data": [
            [
              [
                0.0,
                0.0,
                0.0,
                0.0,
                0.0,
                0.0,
                0.0,
                0.0,
                0.0,
                0.0
              ],
              [
                0.0,
                0.0,
                0.0,
                0.0,
                0.0,
                0.0,
                0.0,
                0.0,
                0.0,
                0.0
              ],
              [
                0.0,
                0.0,
                0.009933801,
                0.011177946,
                0.009303374,
                0.019540883,
                0.032151226,
                0.045097389,
                0.059198044,
                0.074641983
              ]
            ],
            [
              [
                0.0,
                0.0,
                0.0,
                0.0,
                0.0,
                0.0,
                0.0,
                0.0,
                0.0,
                0.0
              ],
              [
                0.0,
                0.0,
                0.0,
                0.0,
                0.0,
                0.0,
                0.0,
                0.0,
                0.0,
                0.0
              ],
              [
                0.0,
                0.0,
                0.009729725,
                0.008436483,
                0.010014681,
                0.021422715,
                0.033457486,
                0.045654703,
                0.062159969,
                0.077837958
              ]
            ],
            [
              [
                0.0,
                0.0,
                0.0,
                0.0,
                0.0,
                0.0,
                0.0,
                0.0,
                0.0,
                0.0
              ],
              [
                0.0,
                0.0,
                0.0,
                0.0,
                0.0,
                0.0,
                0.0,
                0.0,
                0.0,
                0.0
              ],
              [
                0.0,
                0.0,
                0.009851004,
                0.008805328,
                0.010324217,
                0.022339286,
                0.034650508,
                0.04656135,
                0.058805671,
                0.078365293
              ]
            ],
            [
              [
                0.0,
                0.0,
                0.0,
                0.0,
                0.0,
                0.0,
                0.0,
                0.0,
                0.0,
                0.0
              ],
              [
                0.0,
                0.0,
                0.0,
                0.0,
                0.0,
                0.0,
                0.0,
                0.0,
                0.0,
                0.0
              ],
              [
                0.0,
                0.0,
                0.010281796,
                0.009071837,
                0.011029451,
                0.022877028,
                0.035250702,
                0.046857509,
                0.058905473,
                0.079070195
              ]
            ],
            [
              [
                0.0,
                0.0,
                0.0,
                0.0,
                0.0,
                0.0,
                0.0,
                0.0,
                0.0,
                0.0
              ],
              [
                0.0,
                0.0,
                0.0,
                0.0,
                0.0,
                0.0,
                0.0,
                0.0,
                0.0,
                0.0
              ],
              [
                0.0,
                0.0,
                0.011824065,
                0.010432612,
                0.012683869,
                0.026308582,
                0.040538308,
                0.053886135,
                0.067741294,
                0.090930724
              ]
            ]
          ]
        }
      },
      "conduction_loss": [
        {
          "computation_method": "Table only",
          "current_axis": [
            -100.0,
            -75.0,
            -50.0,
            -25.0,
            -10.0,
            -5.0,
            -2.0,
            0.0,
            2.0,
            5.0,
            10.0,
            25.0,
            50.0,
            75.0
          ],
          "temperature_axis": [
            -40.0,
            25.0,
            175.0,
            900.0
          ],
          "voltage_drop": {
            "scale": 1.0,
            "data": [
              [],
              [],
              [],
              []
            ]
          },
          "gate": "on"
        },
        {
          "computation_method": "Table only",
          "current_axis": [
            -100.0,
            -75.0,
            -50.0,
            -25.0,
            -10.0,
            -5.0,
            -0.13,
            0.0,
            1.0
          ],
          "temperature_axis": [
            -40.0,
            25.0,
            175.0,
            900.0
          ],
          "voltage_drop": {
            "scale": 1.0,
            "data": [
              [],
              [],
              [],
              []
            ]
          },
          "gate": "off"
        }
      ]
    },
    "thermal_model": {
      "type": "Cauer",
      "rc_elements": [
        {
          "R": 0.13016,
          "C": 0.000607
        },
        {
          "R": 0.40999,
          "C": 0.00281
        },
        {
          "R": 0.23442,
          "C": 0.01061
        },
        {
          "R": 0.21715,
          "C": 0.08336
        }
      ]
    },
    "comment": [
      "-------------------------------------------------------------------------------------------------",
      "DISCLAIMER",
      "This model is provided as is, where is, and with no warranty of any kind either",
      "expressed or implied, including but not limited to any implied warranties of",
      "merchantability and fitness for a particular purpose.",
      "-------------------------------------------------------------------------------------------------",
      "",
      "",
      "-------------------------------------------------------------------------------------------------",
      "Wolfspeed SiC MOSFET PLECS Library",
      "",
      "       E3M0060065D",
      "       MOSFET",
      "       Datasheet Rev.1, 2025-09-18",
      "       ",
      "       Electrical Parameters (nominal)",
      "       Ron = 0.07 Ω",
      "       Vf = 4.183 V",
      "       ",
      "-------------------------------------------------------------------------------------------------",
      "",
      "",
      "-------------------------------------------------------------------------------------------------",
      "To find other WOLFSPEED SiC models, please visit:",
      "https://www.wolfspeed.com/tools-and-support/power/ltspice-and-plecs-models/",
      "-------------------------------------------------------------------------------------------------"
    ]
  }
}